dot_configs/__init__.py
dot_configs/dot_configs.py
dot_configs-0.1.1.dist-info/AUTHORS.rst
dot_configs-0.1.1.dist-info/LICENSE
dot_configs-0.1.1.dist-info/METADATA
dot_configs-0.1.1.dist-info/WHEEL
dot_configs-0.1.1.dist-info/top_level.txt
dot_configs-0.1.1.dist-info/RECORD
