Metadata-Version: 2.1
Name: dot-configs
Version: 0.1.1
Summary: Import and handle project configurations as dot-separated configs object
Home-page: https://gitlab.com/loxosceles/dot_configs
Author: Magnus "Loxosceles" Henkel
Author-email: loxosceles@gmx.de
License: GNU GPL v3.0
Keywords: dot_configs
Platform: UNKNOWN
Classifier: Development Status :: 2 - Pre-Alpha
Classifier: Intended Audience :: Developers
Classifier: License :: OSI Approved :: GNU General Public License v3 (GPLv3)
Classifier: Natural Language :: English
Classifier: Programming Language :: Python :: 3.5
Classifier: Programming Language :: Python :: 3.6
Classifier: Programming Language :: Python :: 3.7
Classifier: Programming Language :: Python :: Implementation :: PyPy
